pyppetdb/__init__.py
pyppetdb/config.py
pyppetdb/errors.py
pyppetdb/main.py
pyppetdb/authorize/__init__.py
pyppetdb/controller/__init__.py
pyppetdb/controller/api/__init__.py
pyppetdb/controller/api/v1/__init__.py
pyppetdb/controller/api/v1/authenticate.py
pyppetdb/controller/api/v1/nodes.py
pyppetdb/controller/api/v1/nodes_catalogs.py
pyppetdb/controller/api/v1/nodes_groups.py
pyppetdb/controller/api/v1/nodes_reports.py
pyppetdb/controller/api/v1/teams.py
pyppetdb/controller/api/v1/users.py
pyppetdb/controller/api/v1/users_credentials.py
pyppetdb/controller/api/v1/ws.py
pyppetdb/controller/oauth/__init__.py
pyppetdb/controller/oauth/authenticate.py
pyppetdb/controller/pdb/__init__.py
pyppetdb/controller/pdb/cmd/__init__.py
pyppetdb/controller/pdb/cmd/v1.py
pyppetdb/controller/pdb/query/__init__.py
pyppetdb/controller/pdb/query/v4/__init__.py
pyppetdb/controller/pdb/query/v4/resources.py
pyppetdb/crud/__init__.py
pyppetdb/crud/common.py
pyppetdb/crud/credentials.py
pyppetdb/crud/ldap.py
pyppetdb/crud/mixins.py
pyppetdb/crud/nodes.py
pyppetdb/crud/nodes_catalogs.py
pyppetdb/crud/nodes_groups.py
pyppetdb/crud/nodes_reports.py
pyppetdb/crud/oauth.py
pyppetdb/crud/teams.py
pyppetdb/crud/users.py
pyppetdb/model/__init__.py
pyppetdb/model/authenticate.py
pyppetdb/model/common.py
pyppetdb/model/credentials.py
pyppetdb/model/nodes.py
pyppetdb/model/nodes_catalogs.py
pyppetdb/model/nodes_groups.py
pyppetdb/model/nodes_reports.py
pyppetdb/model/oauth.py
pyppetdb/model/pdb_facts.py
pyppetdb/model/teams.py
pyppetdb/model/users.py
pyppetdb-0.0.0.dist-info/METADATA
pyppetdb-0.0.0.dist-info/WHEEL
pyppetdb-0.0.0.dist-info/entry_points.txt
pyppetdb-0.0.0.dist-info/licenses/LICENSE.txt
pyppetdb-0.0.0.dist-info/RECORD
