Metadata-Version: 2.4
Name: pyppetdb
Version: 0.0.0
Summary: PyppedDB is a Python replacment for PuppetDB
Author-email: "Stephan.Schultchen" <stephan.schultchen@gmail.com>
License:                     GNU AFFERO GENERAL PUBLIC LICENSE
License-File: LICENSE.txt
Classifier: Programming Language :: Python
Requires-Python: >=3.9
Requires-Dist: aiofiles==24.1.0
Requires-Dist: annotated-types==0.6.0
Requires-Dist: anyio==4.2.0
Requires-Dist: authlib==1.3.0
Requires-Dist: bonsai==1.5.2
Requires-Dist: certifi==2023.11.17
Requires-Dist: cffi==1.16.0
Requires-Dist: click==8.1.7
Requires-Dist: cryptography==42.0.4
Requires-Dist: dnspython==2.6.1
Requires-Dist: email-validator==2.1.0.post1
Requires-Dist: fastapi-cli==0.0.7
Requires-Dist: fastapi==0.115.6
Requires-Dist: h11==0.14.0
Requires-Dist: httpcore==1.0.2
Requires-Dist: httptools==0.6.4
Requires-Dist: httpx==0.26.0
Requires-Dist: idna==3.7
Requires-Dist: itsdangerous==2.1.2
Requires-Dist: jinja2==3.1.5
Requires-Dist: markdown-it-py==3.0.0
Requires-Dist: markupsafe==3.0.2
Requires-Dist: mdurl==0.1.2
Requires-Dist: motor==3.3.2
Requires-Dist: natsort==8.4.0
Requires-Dist: passlib==1.7.4
Requires-Dist: pycparser==2.21
Requires-Dist: pydantic-core==2.16.1
Requires-Dist: pydantic-settings==2.1.0
Requires-Dist: pydantic==2.6.0
Requires-Dist: pygments==2.18.0
Requires-Dist: pymongo==4.6.3
Requires-Dist: python-dotenv==1.0.1
Requires-Dist: python-multipart==0.0.20
Requires-Dist: pyyaml==6.0.2
Requires-Dist: rich-toolkit==0.12.0
Requires-Dist: rich==13.9.4
Requires-Dist: shellingham==1.5.4
Requires-Dist: sniffio==1.3.0
Requires-Dist: starlette==0.41.3
Requires-Dist: texttable==1.7.0
Requires-Dist: typer==0.15.1
Requires-Dist: typing-extensions==4.12.2
Requires-Dist: uvicorn==0.27.1
Requires-Dist: uvloop==0.21.0
Requires-Dist: watchfiles==1.0.3
Requires-Dist: websockets==14.1
